signal_processing_basics/__init__.py
signal_processing_basics/signal_processing/__init__.py
signal_processing_basics/signal_processing/Order_Tracking.py
signal_processing_basics/signal_processing/signalprocessing.py
signal_processing_basics-0.1.9.dist-info/LICENSE
signal_processing_basics-0.1.9.dist-info/METADATA
signal_processing_basics-0.1.9.dist-info/WHEEL
signal_processing_basics-0.1.9.dist-info/RECORD
