Metadata-Version: 2.3
Name: signal_processing_basics
Version: 0.1.9
Summary: Signal Processing Basics for Condition Monitoring Engineers
Author: Justin Smith
Author-email: 66smithjustin@gmail.com
Maintainer: Justin Smith
Maintainer-email: 66smithjustin@gmail.com
Requires-Python: >=3.11,<4.0
Classifier: Programming Language :: Python :: 3
Classifier: Programming Language :: Python :: 3.11
Classifier: Programming Language :: Python :: 3.12
Classifier: Programming Language :: Python :: 3.13
Requires-Dist: ipykernel (>=6.29.5,<7.0.0)
Requires-Dist: matplotlib (>=3.10.0,<4.0.0)
Requires-Dist: numpy (<2.2)
Requires-Dist: scikit-learn (>=1.6.1,<2.0.0)
Requires-Dist: scipy (>=1.15.1,<2.0.0)
Requires-Dist: statistics (>=1.0.3.5,<2.0.0.0)
Project-URL: Repository, https://github.com/JustinSmith66/Signal-Processing
